sam_doc_gen/__init__.py
sam_doc_gen/yaml_to_html.py
sam_doc_gen/templates/__init__.py
sam_doc_gen/templates/base.py
sam_doc_gen/templates/open_api.py
aubay_sam_deploy-0.0.7.dist-info/LICENSE
aubay_sam_deploy-0.0.7.dist-info/METADATA
aubay_sam_deploy-0.0.7.dist-info/WHEEL
aubay_sam_deploy-0.0.7.dist-info/entry_points.txt
aubay_sam_deploy-0.0.7.dist-info/top_level.txt
aubay_sam_deploy-0.0.7.dist-info/RECORD
