Metadata-Version: 2.1
Name: aubay-sam-deploy
Version: 0.0.7
Summary: AUBAY Sample Deploy project
Author-email: Yovany Dominico Giron <dgiron@aubay.es>, Pedro Vicente Cabrera Rivas <pvcabrera@aubay.es>
License: MIT License
Project-URL: Homepage, https://github.com/AubaySpain/aubay-sam-deploy
Project-URL: Bug Reports, https://github.com/AubaySpain/aubay-sam-deploy/issues
Project-URL: Source, https://github.com/AubaySpain/aubay-sam-deploy/
Keywords: sam_doc_gen,sam_doc_gen.templates,setuptools,development
Classifier: Development Status :: 3 - Alpha
Classifier: Intended Audience :: Developers
Classifier: Topic :: Software Development :: Build Tools
Classifier: License :: OSI Approved :: MIT License
Classifier: Programming Language :: Python :: 3
Classifier: Programming Language :: Python :: 3.7
Classifier: Programming Language :: Python :: 3.8
Classifier: Programming Language :: Python :: 3.9
Classifier: Programming Language :: Python :: 3.10
Classifier: Programming Language :: Python :: 3.11
Classifier: Programming Language :: Python :: 3 :: Only
Requires-Python: >=3.7
License-File: LICENSE
Provides-Extra: dev
Requires-Dist: check-manifest ; extra == 'dev'
Provides-Extra: test
Requires-Dist: coverage ; extra == 'test'
